hiclip/Torchelie/.flake8
hiclip/Torchelie/.git
hiclip/Torchelie/.github/workflows/lint.yml
hiclip/Torchelie/.github/workflows/tests.yml
hiclip/Torchelie/.gitignore
hiclip/Torchelie/.readthedocs.yml
hiclip/Torchelie/LICENSE
hiclip/Torchelie/README.md
hiclip/Torchelie/docs/Makefile
hiclip/Torchelie/docs/_static/css/custom.css
hiclip/Torchelie/docs/_static/dream_example.jpg
hiclip/Torchelie/docs/_static/style_example.png
hiclip/Torchelie/docs/_static/vis_example.jpg
hiclip/Torchelie/docs/_templates/klass.rst
hiclip/Torchelie/docs/callbacks.rst
hiclip/Torchelie/docs/conf.py
hiclip/Torchelie/docs/data_learning.rst
hiclip/Torchelie/docs/datasets.rst
hiclip/Torchelie/docs/distributions.rst
hiclip/Torchelie/docs/hyper.rst
hiclip/Torchelie/docs/index.rst
hiclip/Torchelie/docs/loss.rst
hiclip/Torchelie/docs/make.bat
hiclip/Torchelie/docs/models.rst
hiclip/Torchelie/docs/nn.rst
hiclip/Torchelie/docs/optimizers.rst
hiclip/Torchelie/docs/recipe_tuto.rst
hiclip/Torchelie/docs/recipes.rst
hiclip/Torchelie/docs/transforms.rst
hiclip/Torchelie/docs/utils.rst
hiclip/Torchelie/examples/conditional.py
hiclip/Torchelie/examples/gan.py
hiclip/Torchelie/examples/mnist.py
hiclip/Torchelie/examples/pixelcnn.py
hiclip/Torchelie/logo.png
hiclip/Torchelie/requirements-docs.txt
hiclip/Torchelie/requirements.txt
hiclip/Torchelie/run_tests.sh
hiclip/Torchelie/setup.py
hiclip/Torchelie/tests/dream_me.jpg
hiclip/Torchelie/tests/style.jpg
hiclip/Torchelie/tests/test_datalearning.py
hiclip/Torchelie/tests/test_datasets.py
hiclip/Torchelie/tests/test_loss.py
hiclip/Torchelie/tests/test_models.py
hiclip/Torchelie/tests/test_nn.py
hiclip/Torchelie/tests/test_optims.py
hiclip/Torchelie/tests/test_recipes.py
hiclip/Torchelie/tests/test_sched.py
hiclip/Torchelie/tests/test_tensorboard_callback.py
hiclip/Torchelie/tests/test_tranforms.py
hiclip/Torchelie/tests/test_utils.py
hiclip/Torchelie/torchelie/__init__.py
hiclip/Torchelie/torchelie/callbacks/__init__.py
hiclip/Torchelie/torchelie/callbacks/avg.py
hiclip-0.0.8.dist-info/METADATA
hiclip-0.0.8.dist-info/WHEEL
hiclip-0.0.8.dist-info/licenses/LICENSE
hiclip-0.0.8.dist-info/RECORD
