Metadata-Version: 2.4
Name: hiclip
Version: 0.0.8
Summary: 
License: MIT
License-File: LICENSE
Author: liminghong.dev
Author-email: lmh0066@outlook.com
Requires-Python: >=3.9
Classifier: License :: OSI Approved :: MIT License
Classifier: Programming Language :: Python :: 3
Classifier: Programming Language :: Python :: 3.9
Classifier: Programming Language :: Python :: 3.10
Classifier: Programming Language :: Python :: 3.11
Classifier: Programming Language :: Python :: 3.12
Classifier: Programming Language :: Python :: 3.13
Classifier: Programming Language :: Python :: 3.14
Requires-Dist: botocore (>=1.34.25)
Requires-Dist: captum (>=0.7.0)
Requires-Dist: cooler (>=0.9.3)
Requires-Dist: crayons (>=0.2)
Requires-Dist: numpy (>=1.21.0)
Requires-Dist: rich (>=13.7.0)
Requires-Dist: scvi-tools (>=1.0.4)
Requires-Dist: torch (>=1.12.0)
Requires-Dist: torchvision (>=0.4)
Requires-Dist: visdom (>=0.1.8)
